{
  "downloaded": [
    {
      "doi": "10.1093/poq/nfs038",
      "url": "https://academic-oup-com.proxy.uchicago.edu/poq/article/76/3/405/1894274",
      "title": "Affect, Not Ideology: A Social Identity Perspective on Polarization",
      "authors": "Iyengar, S; Sood, G; Lelkes, Y",
      "year": "2012",
      "filename": "Iyengar et al. - 2012 - Affect Not Ideology A Social Identity Perspective on Polar",
      "method": "scholar_proxy"
    },
    {
      "doi": "10.1146/annurev-polisci-100711-135242",
      "url": "https://www-annualreviews-org.proxy.uchicago.edu/doi/10.1146/annurev-polisci-100711-135242",
      "title": "Media and Political Polarization",
      "authors": "Prior, M",
      "year": "2013",
      "filename": "Prior et al. - 2013 - Media and Political Polarization",
      "method": "direct_proxy"
    },
    {
      "doi": "10.1146/annurev.psych.60.110707.163600",
      "url": "https://www-annualreviews-org.proxy.uchicago.edu/doi/10.1146/annurev.psych.60.110707.163600",
      "title": "Political Ideology: Its Structure, Functions, and Elective Affinities",
      "authors": "Jost, JT; Federico, CM; Napier, JL",
      "year": "2009",
      "filename": "Jost et al. - 2009 - Political Ideology Its Structure Functions and Elective A",
      "method": "direct_proxy"
    },
    {
      "doi": "10.1111/ajps.12152",
      "url": "https://onlinelibrary-wiley-com.proxy.uchicago.edu/doi/10.1111/ajps.12152",
      "title": "Fear and Loathing across Party Lines: New Evidence on Group Polarization",
      "authors": "Iyengar, S; Westwood, SJ",
      "year": "2015",
      "filename": "Iyengar et al. - 2015 - Fear and Loathing across Party Lines New Evidence on Group",
      "method": "direct_proxy"
    },
    {
      "doi": "10.1126/science.abe1715",
      "url": "https://www-science-org.proxy.uchicago.edu/doi/10.1126/science.abe1715",
      "title": "Political Sectarianism in America",
      "authors": "Finkel, EJ; Bail, CA; Cikara, M; et al. (15 authors)",
      "year": "2020",
      "filename": "Finkel et al. - 2020 - Political Sectarianism in America",
      "method": "direct_proxy"
    },
    {
      "doi": "10.1086/693987",
      "url": "https://www-journals-uchicago-edu.proxy.uchicago.edu/doi/10.1086/693987",
      "title": "Americans, Not Partisans: Can Priming American National Identity Reduce Affective Polarization?",
      "authors": "Levendusky, MS",
      "year": "2018",
      "filename": "Levendusky et al. - 2018 - Americans Not Partisans Can Priming American National Iden",
      "method": "direct_proxy"
    },
    {
      "doi": "10.1038/s41562-022-01442-3",
      "url": "https://www-nature-com.proxy.uchicago.edu/articles/s41562-022-01442-3",
      "title": "Interventions to Reduce Partisan Animosity",
      "authors": "Hartman, R; Blakey, W; Sabet, JM; et al.",
      "year": "2022",
      "filename": "Hartman et al. - 2022 - Interventions to Reduce Partisan Animosity",
      "method": "direct_proxy"
    },
    {
      "doi": "10.1073/pnas.1804840115",
      "url": "https://www-pnas-org.proxy.uchicago.edu/doi/full/10.1073/pnas.1804840115",
      "title": "Exposure to Opposing Views on Social Media Can Increase Political Polarization",
      "authors": "Bail, CA; Argyle, LP; Brown, TW; et al.",
      "year": "2018",
      "filename": "Bail et al. - 2018 - Exposure to Opposing Views on Social Media Can Increase Poli",
      "method": "direct_proxy"
    },
    {
      "doi": "10.1073/pnas.1706588114",
      "url": "https://www-pnas-org.proxy.uchicago.edu/doi/full/10.1073/pnas.1706588114",
      "title": "Greater Internet Use Is Not Associated with Faster Growth in Political Polarization",
      "authors": "Boxell, L; Gentzkow, M; Shapiro, JM",
      "year": "2017",
      "filename": "Boxell et al. - 2017 - Greater Internet Use Is Not Associated with Faster Growth in",
      "method": "direct_proxy"
    },
    {
      "doi": "10.1073/pnas.2023301118",
      "url": "https://www-pnas-org.proxy.uchicago.edu/doi/full/10.1073/pnas.2023301118",
      "title": "Echo Chambers on Social Media: A Comparative Analysis",
      "authors": "Cinelli, M; De Francisci Morales, G; Galeazzi, A; Quattrociocchi, W; Starnini, M",
      "year": "2021",
      "filename": "Cinelli et al. - 2021 - Echo Chambers on Social Media A Comparative Analysis",
      "method": "direct_proxy"
    },
    {
      "doi": "10.1177/14614448231207644",
      "url": "https://journals-sagepub-com.proxy.uchicago.edu/doi/10.1177/14614448231207644",
      "title": "A Review and Provocation: On Polarization and Platforms",
      "authors": "Kreiss, D; McGregor, SC",
      "year": "2024",
      "filename": "Kreiss et al. - 2024 - A Review and Provocation On Polarization and Platforms",
      "method": "direct_proxy"
    },
    {
      "doi": "10.1017/S0003055401003045",
      "url": "https://www-cambridge-org.proxy.uchicago.edu/core/journals/american-political-science-review/article/resurgent-mass-partisanship-the-role-of-elite-polarization/2EC5D9D7B192B68C27059C02FCFBA1A3",
      "title": "Resurgent Mass Partisanship: The Role of Elite Polarization",
      "authors": "Hetherington, MJ",
      "year": "2001",
      "filename": "Hetherington et al. - 2001 - Resurgent Mass Partisanship The Role of Elite Polarization",
      "method": "scholar_oa"
    },
    {
      "doi": "10.1086/590649",
      "url": "https://www-journals-uchicago-edu.proxy.uchicago.edu/doi/10.1086/590649",
      "title": "Partisans without Constraint: Political Polarization and Trends in American Public Opinion",
      "authors": "Baldassarri, D; Gelman, A",
      "year": "2008",
      "filename": "Baldassarri et al. - 2008 - Partisans without Constraint Political Polarization and Tre",
      "method": "direct_proxy"
    },
    {
      "doi": "10.7208/chicago/9780226524689.001.0001",
      "url": "https://www.bibliovault.org/BV.landing.epl?ISBN=9780226524689",
      "title": "Uncivil Agreement: How Politics Became Our Identity",
      "authors": "Mason, L",
      "year": "2018",
      "filename": "Mason et al. - 2018 - Uncivil Agreement How Politics Became Our Identity",
      "method": "scholar_oa"
    },
    {
      "doi": "10.1017/S0003055412000500",
      "url": "https://www-cambridge-org.proxy.uchicago.edu/core/journals/american-political-science-review/article/how-elite-partisan-polarization-affects-public-opinion-formation/6CB23BCCFBFBB4EA3879D91232CEEA59",
      "title": "How Elite Partisan Polarization Affects Public Opinion Formation",
      "authors": "Druckman, JN; Peterson, E; Slothuus, R",
      "year": "2013",
      "filename": "Druckman et al. - 2013 - How Elite Partisan Polarization Affects Public Opinion Forma",
      "method": "scholar_oa"
    },
    {
      "doi": "10.1037/0022-3514.37.11.2098",
      "url": "https://doi-apa-org.proxy.uchicago.edu/doi/10.1037/0022-3514.37.11.2098",
      "title": "Biased Assimilation and Attitude Polarization",
      "authors": "Lord, CG; Ross, L; Lepper, MR",
      "year": "1979",
      "filename": "Lord et al. - 1979 - Biased Assimilation and Attitude Polarization",
      "method": "scholar_oa"
    },
    {
      "doi": "10.1016/j.tics.2018.01.004",
      "url": "https://linkinghub-elsevier-com.proxy.uchicago.edu/retrieve/pii/S1364661318300172",
      "title": "The Partisan Brain: An Identity-Based Model of Political Belief",
      "authors": "Van Bavel, JJ; Pereira, A",
      "year": "2018",
      "filename": "Van Bavel et al. - 2018 - The Partisan Brain An Identity-Based Model of Political Bel",
      "method": "scholar_oa"
    },
    {
      "doi": "10.1111/1467-9760.00148",
      "url": "https://onlinelibrary-wiley-com.proxy.uchicago.edu/doi/10.1111/1467-9760.00148",
      "title": "The Law of Group Polarization",
      "authors": "Sunstein, CR",
      "year": "2002",
      "filename": "Sunstein et al. - 2002 - The Law of Group Polarization",
      "method": "direct_proxy"
    },
    {
      "doi": "10.1111/pops.12407",
      "url": "https://onlinelibrary-wiley-com.proxy.uchicago.edu/doi/10.1111/pops.12407",
      "title": "Ideological Asymmetries and the Essence of Political Psychology",
      "authors": "Jost, JT",
      "year": "2017",
      "filename": "Jost et al. - 2017 - Ideological Asymmetries and the Essence of Political Psychol",
      "method": "direct_proxy"
    },
    {
      "doi": "10.1177/0002764218759576",
      "url": "https://journals-sagepub-com.proxy.uchicago.edu/doi/10.1177/0002764218759576",
      "title": "Polarization and the Global Crisis of Democracy",
      "authors": "McCoy, J; Rahman, T; Somer, M",
      "year": "2018",
      "filename": "McCoy et al. - 2018 - Polarization and the Global Crisis of Democracy",
      "method": "direct_proxy"
    },
    {
      "doi": "10.1177/0002716218818782",
      "url": "https://journals-sagepub-com.proxy.uchicago.edu/doi/10.1177/0002716218818782",
      "title": "Polarization and Democracy: A Systematic Review",
      "authors": "Somer, M; McCoy, J",
      "year": "2019",
      "filename": "Somer et al. - 2019 - Polarization and Democracy A Systematic Review",
      "method": "direct_proxy"
    },
    {
      "doi": "10.1177/0010414008315860",
      "url": "https://journals-sagepub-com.proxy.uchicago.edu/doi/10.1177/0010414008315860",
      "title": "The Quantity and Quality of Party Systems",
      "authors": "Dalton, RJ",
      "year": "2008",
      "filename": "Dalton et al. - 2008 - The Quantity and Quality of Party Systems",
      "method": "direct_proxy"
    },
    {
      "doi": "10.1177/000312240707200507",
      "url": "https://journals-sagepub-com.proxy.uchicago.edu/doi/10.1177/000312240707200507",
      "title": "Dynamics of Political Polarization",
      "authors": "Baldassarri, D; Bearman, P",
      "year": "2007",
      "filename": "Baldassarri et al. - 2007 - Dynamics of Political Polarization",
      "method": "direct_proxy"
    },
    {
      "doi": "10.1093/acprof:oso/9780190626594.001.0001",
      "url": "https://academic-oup-com.proxy.uchicago.edu/book/6600",
      "title": "Asymmetric Politics",
      "authors": "Grossmann, M; Hopkins, DA",
      "year": "2016",
      "filename": "Grossmann et al. - 2016 - Asymmetric Politics",
      "method": "scholar_oa"
    },
    {
      "doi": "10.1086/697253",
      "url": "https://www-journals-uchicago-edu.proxy.uchicago.edu/doi/10.1086/697253",
      "title": "The Parties in Our Heads",
      "authors": "Ahler, DJ; Sood, G",
      "year": "2018",
      "filename": "Ahler et al. - 2018 - The Parties in Our Heads",
      "method": "direct_proxy"
    },
    {
      "doi": "10.1111/j.1460-2466.2010.01497.x",
      "url": "https://academic-oup-com.proxy.uchicago.edu/joc/article/60/3/556/4098564",
      "title": "Polarization and Partisan Selective Exposure",
      "authors": "Stroud, NJ",
      "year": "2010",
      "filename": "Stroud et al. - 2010 - Polarization and Partisan Selective Exposure",
      "method": "direct_proxy"
    },
    {
      "doi": "10.1038/s41591-024-02879-1",
      "url": "https://doi-org.proxy.uchicago.edu/10.1038/s41591-024-02879-1",
      "title": "Political Polarization and Health",
      "authors": "Van Bavel, JJ; et al.",
      "year": "2024",
      "filename": "Van Bavel et al. - 2024 - Political Polarization and Health",
      "method": "scholar_oa"
    },
    {
      "doi": "10.1257/aer.20190658",
      "url": "https://www-aeaweb-org.proxy.uchicago.edu/articles?id=10.1257/aer.20190658",
      "title": "The Welfare Effects of Social Media",
      "authors": "Allcott, H; Braghieri, L; Enikopolov, R; Gentzkow, M",
      "year": "2020",
      "filename": "Allcott et al. - 2020 - The Welfare Effects of Social Media",
      "method": "direct_proxy"
    }
  ],
  "failed": [
    {
      "doi": "10.1146/annurev-polisci-051418-122950",
      "url": "https://doi-org.proxy.uchicago.edu/10.1146/annurev-polisci-051418-122950",
      "title": "What We Know and Do Not Know About Our Polarized Politics",
      "authors": "McCarty, N",
      "year": "2019",
      "filename": "McCarty et al. - 2019 - What We Know and Do Not Know About Our Polarized Politics"
    },
    {
      "doi": "10.1016/j.cobeha.2020.03.008",
      "url": "https://linkinghub-elsevier-com.proxy.uchicago.edu/retrieve/pii/S2352154620300450",
      "title": "Polarization in America: Two Possible Futures",
      "authors": "Heltzel, G; Laurin, K",
      "year": "2020",
      "filename": "Heltzel et al. - 2020 - Polarization in America Two Possible Futures"
    },
    {
      "doi": "10.1017/S0022381608080493",
      "url": "https://www-journals-uchicago-edu.proxy.uchicago.edu/doi/10.1017/S0022381608080493",
      "title": "Is Polarization a Myth?",
      "authors": "Abramowitz, AI; Saunders, KL",
      "year": "2008",
      "filename": "Abramowitz et al. - 2008 - Is Polarization a Myth"
    },
    {
      "doi": "10.1177/0010414019858524",
      "url": "https://doi-org.proxy.uchicago.edu/10.1177/0010414019858524",
      "title": "Affective Polarization in Multiparty Systems",
      "authors": "Gidron, N; Adams, J; Horne, W",
      "year": "2020",
      "filename": "Gidron et al. - 2020 - Affective Polarization in Multiparty Systems"
    },
    {
      "doi": "10.1017/CBO9781139878425",
      "url": "https://www-cambridge-org.proxy.uchicago.edu/core/books/postbroadcast-democracy/A0D17A3CD156A0D1BB4318EE5DBCC60B",
      "title": "Post-Broadcast Democracy",
      "authors": "Prior, M",
      "year": "2007",
      "filename": "Prior et al. - 2007 - Post-Broadcast Democracy"
    },
    {
      "doi": "10.1146/annurev-economics-012420-105110",
      "url": "https://doi-org.proxy.uchicago.edu/10.1146/annurev-economics-012420-105110",
      "title": "Political Effects of the Internet and Social Media",
      "authors": "Zhuravskaya, E; Petrova, M; Enyedi, R",
      "year": "2020",
      "filename": "Zhuravskaya et al. - 2020 - Political Effects of the Internet and Social Media"
    },
    {
      "doi": "10.1093/poq/nfw006",
      "url": "https://academic-oup-com.proxy.uchicago.edu/poq/article/80/S1/298/2223402",
      "title": "Political Echo Chambers in Online News Consumption",
      "authors": "Flaxman, S; Goel, S; Rao, JM",
      "year": "2016",
      "filename": "Flaxman et al. - 2016 - Political Echo Chambers in Online News Consumption"
    },
    {
      "doi": "10.2139/ssrn.3144139",
      "url": "https://papers.ssrn.com/sol3/papers.cfm?abstract_id=3144139",
      "title": "Social Media and Democracy: The State of the Field",
      "authors": "Tucker, JA; Guess, A; Barbera, P; et al.",
      "year": "2018",
      "filename": "Tucker et al. - 2018 - Social Media and Democracy The State of the Field"
    },
    {
      "doi": "10.1103/PhysRevLett.127.048301",
      "url": "https://doi-org.proxy.uchicago.edu/10.1103/PhysRevLett.127.048301",
      "title": "Modeling Echo Chambers and Polarization Dynamics in Social Networks",
      "authors": "Sasahara, K; Chen, W; Peng, H; et al.",
      "year": "2021",
      "filename": "Sasahara et al. - 2021 - Modeling Echo Chambers and Polarization Dynamics in Social N"
    },
    {
      "doi": "10.12840/ISSN.2255-4165.028",
      "url": "https://rcommunicationr.org/index.php/rcr/article/view/16/16",
      "title": "Echo Chambers on Social Media: A Systematic Review of the Literature",
      "authors": "Terren, L; Borge, R",
      "year": "2021",
      "filename": "Terren et al. - 2021 - Echo Chambers on Social Media A Systematic Review of the Li"
    },
    {
      "doi": "10.1016/j.cobeha.2020.07.005",
      "url": "https://linkinghub-elsevier-com.proxy.uchicago.edu/retrieve/pii/S2352154620301078",
      "title": "Polarization in the Contemporary Political and Media Landscape",
      "authors": "Wilson, AE; Parker, VA; Feinberg, M",
      "year": "2020",
      "filename": "Wilson et al. - 2020 - Polarization in the Contemporary Political and Media Landsca"
    },
    {
      "doi": "10.1016/j.techfore.2022.121942",
      "url": "https://linkinghub-elsevier-com.proxy.uchicago.edu/retrieve/pii/S0040162522004632",
      "title": "Polarization and Social Media: A Systematic Review and Research Agenda",
      "authors": "Arora, SD; Singh, GP; Maity, M",
      "year": "2022",
      "filename": "Arora et al. - 2022 - Polarization and Social Media A Systematic Review and Resea"
    },
    {
      "doi": "10.2307/3088434",
      "url": "https://www-jstor-org.proxy.uchicago.edu/stable/3088434?origin=crossref",
      "title": "Party Polarization and \"Conflict Extension\" in the American Electorate",
      "authors": "Layman, GC; Carsey, TM",
      "year": "2002",
      "filename": "Layman et al. - 2002 - Party Polarization and Conflict Extension in the American"
    },
    {
      "doi": "10.1017/CBO9781139032490",
      "url": "https://www-cambridge-org.proxy.uchicago.edu/core/books/rationalizing-voter/9E4E27965B612D5DDB1091BD907DF492",
      "title": "The Rationalizing Voter",
      "authors": "Lodge, M; Taber, CS",
      "year": "2013",
      "filename": "Lodge et al. - 2013 - The Rationalizing Voter"
    },
    {
      "doi": "10.1037/0022-3514.50.6.1141",
      "url": "https://doi-apa-org.proxy.uchicago.edu/doi/10.1037/0022-3514.50.6.1141",
      "title": "Group Polarization: A Critical Review and Meta-Analysis",
      "authors": "Isenberg, DJ",
      "year": "1986",
      "filename": "Isenberg et al. - 1986 - Group Polarization A Critical Review and Meta-Analysis"
    },
    {
      "doi": "10.1016/j.copsyc.2021.06.005",
      "url": "https://linkinghub-elsevier-com.proxy.uchicago.edu/retrieve/pii/S2352250X21000749",
      "title": "False Polarization: Cognitive Mechanisms and Potential Solutions",
      "authors": "Fernbach, PM; Van Boven, L",
      "year": "2022",
      "filename": "Fernbach et al. - 2022 - False Polarization Cognitive Mechanisms and Potential Solut"
    },
    {
      "doi": "10.1016/j.cobeha.2022.101101",
      "url": "https://linkinghub-elsevier-com.proxy.uchicago.edu/retrieve/pii/S2352154622000018",
      "title": "The Prime Psychological Suspects of Toxic Political Polarization",
      "authors": "Moore-Berg, SL; Hameiri, B; Bruneau, E",
      "year": "2022",
      "filename": "Moore-Berg et al. - 2022 - The Prime Psychological Suspects of Toxic Political Polariza"
    },
    {
      "doi": "10.1515/9780691216508",
      "url": "https://chooser-crossref-org.proxy.uchicago.edu/?doi=10.1515%2F9780691216508",
      "title": "Breaking the Social Media Prism",
      "authors": "Bail, C",
      "year": "2021",
      "filename": "Bail et al. - 2021 - Breaking the Social Media Prism"
    }
  ]
}